SEQ/FETCH/fetch.v
module fetch (
    input clk,
    input [63:0] PC,
    output reg [3:0] icode,
    output reg [3:0] ifun,
    output reg [3:0] rA,
    output reg [3:0] rB,
    output reg [63:0] valC,
    output reg [63:0] valP,
    output reg instruction_valid,
    output reg imem_error,
    output reg halt
);


reg [7:0] instruction_memory[0:1023]; // 1kb instruction_memory
reg [0:79] instr; 

always @(posedge clk) begin
    //Reading first 10 bytes from PC 
    instr[0:7] = instruction_memory[PC];
    instr[8:15] = instruction_memory[PC+1];
    instr[16:23] = instruction_memory[PC+2];
    instr[24:31] = instruction_memory[PC+3];
    instr[32:39] = instruction_memory[PC+4];
    instr[40:47] = instruction_memory[PC+5];
    instr[48:55] = instruction_memory[PC+6];
    instr[56:63] = instruction_memory[PC+7];
    instr[64:71] = instruction_memory[PC+8];
    instr[72:79]  = instruction_memory[PC+9];
      
    // Imem_error
    imem_error = 0;
    if (PC > 1023) begin 
        imem_error = 1;
    end

    // Split
    icode = instr[0:3];
    ifun = instr[4:7];
    halt = 1'h0;
    // Align
    if (icode == 4'h0) begin
        rA <= 4'b1111;
        rB <= 4'b1111;
        valC <= 64'b0;
        instruction_valid <= 1'h1; 
        valP<=PC+64'h1;
        halt <= 1'h1;

    end
    else if (icode == 4'h1) begin
        // rA = 4'b1111;
        // rB = 4'b1111;
        valC = 64'b0;
        instruction_valid = 1'b1;
        valP=PC+64'h1;
    end
    else if (icode == 4'h2) begin
        if (ifun >= 4'h0 && ifun < 4'h7) begin
            rA = instr[8:11];
            rB = instr[12:15];
            valC = 64'b0;
            instruction_valid = 1'b1;
            valP=PC+64'h2;
        end
        else begin
            instruction_valid = 1'b0;
            valP=PC+64'h2;
        end
    end
    else if (icode == 4'h3 || icode == 4'h4 || icode == 4'h5) begin
        rA = instr[8:11];
        rB = instr[12:15];
        valC = instr[16:79];
        instruction_valid = 1'b1;
        valP=PC+64'd10;
    end
    else if (icode == 4'h6) begin
        if (ifun >= 4'h0 && ifun < 4'h4) begin
            rA = instr[8:11];
            rB = instr[12:15];
            valC = 64'b0;
            instruction_valid = 1'b1;
            valP=PC+64'h2;
        end
        else begin
            instruction_valid = 1'b0;
            valP=PC+64'h2;
        end
    end
    else if (icode == 4'h7) begin
        if (ifun >= 4'h0 && ifun < 4'h7) begin
            rA = 4'b1111;
            rB = 4'b1111;
            valC = instr[16:79];
            instruction_valid = 1'b1;
            valP=PC+64'h9;
        end
        else begin
            instruction_valid = 1'b1;
            valP=PC+64'h9;
        end
    end
    else if (icode == 4'h8) begin
        rA = 4'b1111;
        rB = 4'b1111;
        valC = instr[16:79];
        instruction_valid = 1'b1;
        valP=PC+64'h9;
    end
    else if (icode == 4'h9) begin
        rA = 4'b1111;
        rB = 4'b1111;
        valC = 64'b0;
        instruction_valid = 1'b1; 
        valP=PC+64'h1;
    end
    else if (icode == 4'ha || icode == 4'hb) begin
        rA = instr[8:11];
        rB = instr[12:15];
        valC = 64'b0;
        instruction_valid = 1'b1;
        valP=PC+64'h2;
    end
    else begin
        instruction_valid = 1'b0;
    end


end

initial begin
//cmovxx
instruction_memory[0]=8'h20; //2 fn (Conditional Move instruction)
instruction_memory[1]=8'h13; //rA rB

//irmovq
instruction_memory[2]=8'h30; //3 0 (Immediate Load instruction)
instruction_memory[3]=8'h02; //F rB
instruction_memory[4]=8'h00; //V
instruction_memory[5]=8'h00; //V
instruction_memory[6]=8'h00; //V
instruction_memory[7]=8'h00; //V
instruction_memory[8]=8'h00; //V
instruction_memory[9]=8'h00; //V
instruction_memory[10]=8'h00; //V
instruction_memory[11]=8'h10; //V=16

//rmmovq
instruction_memory[12]=8'h40; //4 0 (Register to Memory Move instruction)
instruction_memory[13]=8'h52; //rA rB
instruction_memory[14]=8'h00; //D
instruction_memory[15]=8'h00; //D
instruction_memory[16]=8'h00; //D
instruction_memory[17]=8'h00; //D
instruction_memory[18]=8'h00; //D
instruction_memory[19]=8'h00; //D
instruction_memory[20]=8'h00; //D
instruction_memory[21]=8'h01; //D

//mrmovq
instruction_memory[22]=8'h50; //5 0 (Memory to Register Move instruction)
instruction_memory[23]=8'h72; //rA rB
instruction_memory[24]=8'h00; //D
instruction_memory[25]=8'h00; //D
instruction_memory[26]=8'h00; //D
instruction_memory[27]=8'h00; //D
instruction_memory[28]=8'h00; //D
instruction_memory[29]=8'h00; //D
instruction_memory[30]=8'h00; //D
instruction_memory[31]=8'h01; //D

//halt
instruction_memory[32]=8'h00; // 0 0 (Halt instruction)

//addq
instruction_memory[33]=8'h60; //6 fn (Add instruction)
instruction_memory[34]=8'h23; //rA rB

//subq
instruction_memory[35]=8'h61; //6 fn (Subtract instruction)
instruction_memory[36]=8'h23; //rA rB

//xorq
instruction_memory[37]=8'h63; //6 fn (XOR instruction)
instruction_memory[38]=8'h23; //rA rB

//andq
instruction_memory[39]=8'h62; //6 fn (AND instruction)
instruction_memory[40]=8'h23; //rA rB

//cmovxx
instruction_memory[41]=8'h20; //2 fn (Conditional Move instruction)
instruction_memory[42]=8'h04; //rA rB

instruction_memory[43]=8'h10; // 1 0
instruction_memory[44]=8'h10; // 1 0
instruction_memory[45]=8'h10; // 1 0
instruction_memory[46]=8'h10; // 1 0
instruction_memory[47]=8'h10; // 1 0
instruction_memory[48]=8'h10; // 1 0

//halt
instruction_memory[49]=8'h00; // 0 0

instruction_memory[50]=8'h10; // 1 0

//halt
instruction_memory[51]=8'h00; // 0 0

//cmovxx
instruction_memory[52]=8'h25; //2 fn (Conditional Move instruction)
instruction_memory[53]=8'h04; //rA rB

//jxx
instruction_memory[54]=8'h70; //7 fn (Jump instruction)
instruction_memory[55]=8'h00; //Dest
instruction_memory[56]=8'h00; //Dest
instruction_memory[57]=8'h00; //Dest
instruction_memory[58]=8'h00; //Dest
instruction_memory[59]=8'h00; //Dest
instruction_memory[60]=8'h00; //Dest
instruction_memory[61]=8'h00; //Dest
instruction_memory[62]=8'h20; //Dest

instruction_memory[63]=8'h10; //1 0

//call
instruction_memory[64]=8'h80; //8 0 (Call subroutine instruction)
instruction_memory[65]=8'h00; //Dest
instruction_memory[66]=8'h00; //Dest
instruction_memory[67]=8'h00; //Dest
instruction_memory[68]=8'h00; //Dest
instruction_memory[69]=8'h00; //Dest
instruction_memory[70]=8'h00; //Dest
instruction_memory[71]=8'h00; //Dest
instruction_memory[72]=8'h01; //Dest

//ret
instruction_memory[73]=8'h90; // 9 0 (Return from subroutine instruction)

//halt
instruction_memory[74]=8'h00; // 0 0

//pushq
instruction_memory[75]=8'hA0; //A 0 (Push instruction)
instruction_memory[76]=8'h00; //rA F

//popq
instruction_memory[77]=8'hB0; //B 0 (Pop instruction)
instruction_memory[78]=8'h00; //rA F

//nop
instruction_memory[79]=8'h10; //1 0 (No operation instruction)

//halt 
instruction_memory[80]=8'h00; // 0 0


// //irmovq $0x100, %rbx
//     instruction_memory[0] = 8'b00110000;
//     instruction_memory[1] = 8'b00000011;
//     instruction_memory[2] = 8'b00000000;
//     instruction_memory[3] = 8'b00000001;
//     instruction_memory[4] = 8'b00000000;
//     instruction_memory[5] = 8'b00000000;
//     instruction_memory[6] = 8'b00000000;
//     instruction_memory[7] = 8'b00000000;
//     instruction_memory[8] = 8'b00000000;
//     instruction_memory[9] = 8'b11110011;
    
//     // irmovq $0x200, %rdx
//     instruction_memory[10] = 8'b00110000;
//     instruction_memory[11] = 8'b00000010;
//     instruction_memory[12] = 8'b00000000;
//     instruction_memory[13] = 8'b00000010;
//     instruction_memory[14] = 8'b00000000;
//     instruction_memory[15] = 8'b00000000;
//     instruction_memory[16] = 8'b00000000;
//     instruction_memory[17] = 8'b00000000;
//     instruction_memory[18] = 8'b00000000;
//     instruction_memory[19] = 8'b11110010;
    
//     // addq %rdx, %rbx
//     instruction_memory[20] = 8'b01100000;
//     instruction_memory[21] = 8'b00100011;
//     instruction_memory[22] = 8'b00000000;
//     instruction_memory[23] = 8'b00000000;
//     instruction_memory[24] = 8'b00000000;
//     instruction_memory[25] = 8'b00000000;
//     instruction_memory[26] = 8'b00000000;
//     instruction_memory[27] = 8'b00000000;
//     instruction_memory[28] = 8'b00000000;
//     instruction_memory[29] = 8'b00000000;
// instruction_memory[30]=8'h00; // 0 0
end


endmodule

SEQ/FETCH/tb_fetch.v
module tb_fetch();
    reg clk;
    reg [63:0] PC;
    wire [3:0] icode;
    wire [3:0] ifun;
    wire [3:0] rA;
    wire [3:0] rB;
    wire [63:0] valC;
    wire [63:0] valP;
    wire instruction_valid;
    wire imem_error;
    wire halt;

    fetch tb_fetch(clk, PC, icode, ifun, rA, rB, valC, valP, instruction_valid, imem_error, halt);
  
    initial begin
        $dumpfile("fetch.vcd");
        $dumpvars(0, tb_fetch);
        $monitor("time = %0t , icode = %b , ifun = %b , rA = %b , rB = %b , valC = %d , valP = %d, imem_error = %b, instruction_valid = %b, halt = %b", $time, icode, ifun, rA, rB, valC, valP, imem_error, instruction_valid, halt);

        clk = 0;
        PC = 64'd0;

        for (integer i = 0; i < 57; i = i + 1) begin
            #5 clk = ~clk; 
            #5 PC = valP; 
        end
        $finish;
    end
endmodule

SEQ/FETCH/fetch.vcd
$date
	Thu Feb 22 14:11:45 2024
$end
$version
	Icarus Verilog
$end
$timescale
	1s
$end
$scope module tb_fetch $end
$scope module tb_fetch $end
$var wire 64 ! PC [63:0] $end
$var wire 1 " clk $end
$var reg 1 # halt $end
$var reg 4 $ icode [3:0] $end
$var reg 4 % ifun [3:0] $end
$var reg 1 & imem_error $end
$var reg 80 ' instr [0:79] $end
$var reg 1 ( instruction_valid $end
$var reg 4 ) rA [3:0] $end
$var reg 4 * rB [3:0] $end
$var reg 64 + valC [63:0] $end
$var reg 64 , valP [63:0] $end
$upscope $end
$upscope $end
$enddefinitions $end
#0
$dumpvars
bx ,
bx +
bx *
bx )
x(
bx '
x&
bx %
bx $
x#
0"
b0 !
$end
#5
b10 ,
1(
b0 +
b11 *
b1 )
0#
b0 %
b10 $
0&
b100000000100110011000000000010000000000000000000000000000000000000000000000000 '
1"
#10
b10 !
#15
0"
#25
b1100 ,
b10000 +
b10 *
b0 )
b11 $
b110000000000100000000000000000000000000000000000000000000000000000000000010000 '
1"
#30
b1100 !
#35
0"
#45
b10110 ,
b1 +
b101 )
b100 $
b1000000010100100000000000000000000000000000000000000000000000000000000000000001 '
1"
#50
b10110 !
#55
0"
#65
b100000 ,
b111 )
b101 $
b1010000011100100000000000000000000000000000000000000000000000000000000000000001 '
1"
#70
b100000 !
#75
0"
#85
1#
b100001 ,
b0 +
b1111 *
b1111 )
b0 $
b11000000010001101100001001000110110001000100011011000110010001100100000 '
1"
#90
b100001 !
#95
0"
#105
b100011 ,
b11 *
b10 )
0#
b110 $
b1100000001000110110000100100011011000100010001101100011001000110010000000000100 '
1"
#110
b100011 !
#115
0"
#125
b100101 ,
b1 %
b1100001001000110110001000100011011000110010001100100000000001000001000000010000 '
1"
#130
b100101 !
#135
0"
#145
b100111 ,
b10 %
b1100010001000110110001100100011001000000000010000010000000100000001000000010000 '
1"
#150
b100111 !
#155
0"
#165
b101001 ,
b11 %
b1100011001000110010000000000100000100000001000000010000000100000001000000010000 '
1"
#170
b101001 !
#175
0"
#185
b101011 ,
b100 *
b0 )
b0 %
b10 $
b100000000001000001000000010000000100000001000000010000000100000000000000010000 '
1"
#190
b101011 !
#195
0"
#205
b101100 ,
b1111 *
b1111 )
b1 $
b10000000100000001000000010000000100000001000000000000000100000000000000100101 '
1"
#210
b101100 !
#215
0"
#225
b101101 ,
b10000000100000001000000010000000100000000000000010000000000000010010100000100 '
1"
#230
b101101 !
#235
0"
#245
b101110 ,
b10000000100000001000000010000000000000001000000000000001001010000010001110000 '
1"
#250
b101110 !
#255
0"
#265
b101111 ,
b10000000100000001000000000000000100000000000000100101000001000111000000000000 '
1"
#270
b101111 !
#275
0"
#285
b110000 ,
b10000000100000000000000010000000000000010010100000100011100000000000000000000 '
1"
#290
b110000 !
#295
0"
#305
b110001 ,
b10000000000000001000000000000001001010000010001110000000000000000000000000000 '
1"
#310
b110001 !
#315
0"
#325
1#
b110010 ,
b0 $
b100000000000000100101000001000111000000000000000000000000000000000000 '
1"
#330
b110010 !
#335
0"
#345
b110011 ,
0#
b1 $
b10000000000000010010100000100011100000000000000000000000000000000000000000000 '
1"
#350
b110011 !
#355
0"
#365
1#
b110100 ,
b0 $
b1001010000010001110000000000000000000000000000000000000000000000000000 '
1"
#370
b110100 !
#375
0"
#385
b110110 ,
b100 *
b0 )
0#
b101 %
b10 $
b100101000001000111000000000000000000000000000000000000000000000000000000000000 '
1"
#390
b110110 !
#395
0"
#405
b111111 ,
b10000000010000 +
b1111 *
b1111 )
b0 %
b111 $
b1110000000000000000000000000000000000000000000000000000000000000010000000010000 '
1"
#410
b111111 !
#415
0"
#425
b1000000 ,
b0 +
b1 $
b10000100000000000000000000000000000000000000000000000000000000000000000000001 '
1"
#430
b1000000 !
#435
0"
#445
b1001001 ,
b110010000 +
b1000 $
b10000000000000000000000000000000000000000000000000000000000000000000000110010000 '
1"
#450
b1001001 !
#455
0"
#465
b1001010 ,
b0 +
b1001 $
b1001000000000000101000000000000010110000000000000001000000000000xxxxxxxxxxxxxxxx '
1"
#470
b1001010 !
#475
0"
#485
1#
b1001011 ,
b0 $
b101000000000000010110000000000000001000000000000xxxxxxxxxxxxxxxxxxxxxxxx '
1"
#490
b1001011 !
#495
0"
#505
b1001101 ,
b0 *
b0 )
0#
b1010 $
b101000000000000010110000000000000001000000000000xxxxxxxxxxxxxxxxxxxxxxxxxxxxxxxx '
1"
#510
b1001101 !
#515
0"
#525
b1001111 ,
b1011 $
b10110000000000000001000000000000xxxxxxxxxxxxxxxxxxxxxxxxxxxxxxxxxxxxxxxxxxxxxxxx '
1"
#530
b1001111 !
#535
0"
#545
b1010000 ,
b1111 *
b1111 )
b1 $
b1000000000000xxxxxxxxxxxxxxxxxxxxxxxxxxxxxxxxxxxxxxxxxxxxxxxxxxxxxxxxxxxxxxxx '
1"
#550
b1010000 !
#555
0"
#565
1#
b1010001 ,
b0 $
b0xxxxxxxxxxxxxxxxxxxxxxxxxxxxxxxxxxxxxxxxxxxxxxxxxxxxxxxxxxxxxxxxxxxxxxxx '
1"
#570
b1010001 !
